regenx/__about__.py
regenx/__init__.py
regenx/escapes.py
regenx/main.py
regenx/regenx.py
regenx-0.0.2.dist-info/METADATA
regenx-0.0.2.dist-info/WHEEL
regenx-0.0.2.dist-info/licenses/LICENSE.txt
regenx-0.0.2.dist-info/RECORD
