Metadata-Version: 2.4
Name: regenx
Version: 0.0.2
Summary: yet another regex based text generation library
Project-URL: Homepage, https://github.com/0000matteo0000/regenx
Project-URL: Documentation, https://github.com/0000matteo0000/regenx#readme
Project-URL: Issues, https://github.com/0000matteo0000/regenx/issues
Project-URL: Source, https://github.com/0000matteo0000/regenx
Author-email: 0000matteo0000 <matteo.sid@hotmail.it>
License-Expression: MIT
License-File: LICENSE.txt
Keywords: data-generation,regex,regular-expression,string-generation
Classifier: Development Status :: 4 - Beta
Classifier: License :: OSI Approved :: MIT License
Classifier: Operating System :: OS Independent
Classifier: Programming Language :: Python
Classifier: Programming Language :: Python :: 3
Classifier: Programming Language :: Python :: 3.10
Classifier: Programming Language :: Python :: 3.11
Classifier: Programming Language :: Python :: 3.12
Classifier: Programming Language :: Python :: Implementation :: CPython
Classifier: Programming Language :: Python :: Implementation :: PyPy
Requires-Python: >=3.10
Provides-Extra: dev
Requires-Dist: autopep8; extra == 'dev'
Requires-Dist: isort; extra == 'dev'
Requires-Dist: pytest; extra == 'dev'
Requires-Dist: pytest-cov; extra == 'dev'
Provides-Extra: formatting
Requires-Dist: autopep8; extra == 'formatting'
Requires-Dist: isort; extra == 'formatting'
Provides-Extra: testing
Requires-Dist: pytest; extra == 'testing'
Requires-Dist: pytest-cov; extra == 'testing'
